<?xml version='1.0' encoding='UTF-8'?>
<Msg>
	<Head>
		<VerCode>2015101901</VerCode>
		<ReqSysCode>01</ReqSysCode>
		<TxMode>S</TxMode>
		<TxCode>000008</TxCode>
		<ReqDateTime>20151019000000</ReqDateTime>
		<ReqSeqNo>testmytest</ReqSeqNo>
		<SvrDateTime></SvrDateTime>
		<SvrSeqNo></SvrSeqNo>
		<ChanlNo>DSK</ChanlNo>
		<OrgNo>791100</OrgNo>
		<TermNo></TermNo>
		<OperNo>910057</OperNo>
	</Head>
	<Body>
		<DataStores>
			<TRADE_TYPE>JH</TRADE_TYPE>
			<OCCUPY_LMT_STATUS>Y</OCCUPY_LMT_STATUS>
			<BIZ_TYPE_CODE>01</BIZ_TYPE_CODE>
			<IDTYPE_CODE>I01</IDTYPE_CODE>
			<IDCODE>421122199106132110</IDCODE>
			<CTYCODE>CHN</CTYCODE>
			<ADD_IDCODE></ADD_IDCODE>
			<PERSON_NAME>wuhan</PERSON_NAME>
			<TX_CODE>110</TX_CODE>
			<SALEFX_SETTLE_CODE>01</SALEFX_SETTLE_CODE>
			<TXCCY>840</TXCCY>
			<TXAMT>00000000000000.00</TXAMT>
			<PURFX_CASH_AMT>00000000000000.00</PURFX_CASH_AMT>
			<FCY_REMIT_AMT>00000000000000.00</FCY_REMIT_AMT>
			<FCY_ACCT_AMT>00000000000000.00</FCY_ACCT_AMT>
			<TCHK_AMT>00000000000000.00</TCHK_AMT>
			<LCY_ACCTNO_CNY></LCY_ACCTNO_CNY>
			<LCY_ACCT_NO></LCY_ACCT_NO>
			<SIGNSTATUS>Y</SIGNSTATUS>
			<AGENT_CORP_CODE></AGENT_CORP_CODE>
			<AGENT_CORP_NAME></AGENT_CORP_NAME>
			<INDIV_ORG_CODE></INDIV_ORG_CODE>
			<INDIV_ORG_NAME></INDIV_ORG_NAME>
			<PAY_ORG_CODE></PAY_ORG_CODE>
			<CAPITALNO></CAPITALNO>
			<BIZ_TX_TIME>2016010400</BIZ_TX_TIME>
			<REMARK></REMARK>
			<REIN_REASON_CODE>01</REIN_REASON_CODE>
			<REIN_REMARK></REIN_REMARK>
		</DataStores>
	</Body>
</Msg>